Akc/Bitwise.py
Akc/FibonacciGenerator.py
Akc/TCKimlik.py
Akc/VergiKimlik.py
Akc/__init__.py
Akc-0.3.dist-info/LICENSE
Akc-0.3.dist-info/METADATA
Akc-0.3.dist-info/WHEEL
Akc-0.3.dist-info/top_level.txt
Akc-0.3.dist-info/RECORD
