Metadata-Version: 2.1
Name: Akc
Version: 0.3
Summary: Akc.base deneme.
Author: Hasan AKÇAKOCA
Author-email: hasanakcakoca@gmail.com
Requires-Python: >=3
License-File: LICENSE
